poimport.py
poimport-1.1.dist-info/COPYING
poimport-1.1.dist-info/METADATA
poimport-1.1.dist-info/WHEEL
poimport-1.1.dist-info/top_level.txt
poimport-1.1.dist-info/RECORD
